llama_index/llms/vercel_ai_gateway/__init__.py
llama_index/llms/vercel_ai_gateway/base.py
llama_index_llms_vercel_ai_gateway-0.1.1.dist-info/METADATA
llama_index_llms_vercel_ai_gateway-0.1.1.dist-info/WHEEL
llama_index_llms_vercel_ai_gateway-0.1.1.dist-info/licenses/LICENSE
llama_index_llms_vercel_ai_gateway-0.1.1.dist-info/RECORD
